SEM-3/Verilog-Codes/lab9/async.v
module tff(t,clk,reset,q);
input t,clk,reset;
output reg q;
always @(negedge clk or posedge reset)
begin
  if(reset) q<=1'b0;
  else
    begin
      if(t==1'b0) q<=q;
      else q<=~q;
    end
end
endmodule

module async(clk,reset,w);
input clk,reset;
output [3:0]w;
tff stg0(1'b1,clk,reset,w[3]);
tff stg1(1'b1,w[3],reset,w[2]);
tff stg2(1'b1,w[2],reset,w[1]);
tff stg3(1'b1,w[1],reset,w[0]);
endmodule

SEM-3/Verilog-Codes/lab9/async_tb.v
`timescale 1ns/1ns
`include "async.v"
module async_tb;
reg clk,reset;
wire [3:0]w;
async uut(clk,reset,w);
initial begin
  $dumpfile("async_tb.vcd");
  $dumpvars(0,async_tb);
  clk=0;
  forever #10 clk=~clk;
end
initial begin
  reset=1; #20
  reset=0; #160
  $display("Test complete");
  $finish;
end
endmodule

SEM-3/Verilog-Codes/lab9/async_tb.vcd
$date
	Tue Nov 21 18:14:07 2023
$end
$version
	Icarus Verilog
$end
$timescale
	1ns
$end
$scope module async_tb $end
$var wire 4 ! w [3:0] $end
$var reg 1 " clk $end
$var reg 1 # reset $end
$scope module uut $end
$var wire 1 $ clk $end
$var wire 1 % reset $end
$var wire 4 & w [3:0] $end
$scope module stg0 $end
$var wire 1 $ clk $end
$var wire 1 % reset $end
$var wire 1 ' t $end
$var reg 1 ( q $end
$upscope $end
$scope module stg1 $end
$var wire 1 ) clk $end
$var wire 1 % reset $end
$var wire 1 * t $end
$var reg 1 + q $end
$upscope $end
$scope module stg2 $end
$var wire 1 , clk $end
$var wire 1 % reset $end
$var wire 1 - t $end
$var reg 1 . q $end
$upscope $end
$scope module stg3 $end
$var wire 1 / clk $end
$var wire 1 % reset $end
$var wire 1 0 t $end
$var reg 1 1 q $end
$upscope $end
$upscope $end
$upscope $end
$enddefinitions $end
#0
$dumpvars
01
10
0/
0.
1-
0,
0+
1*
0)
0(
1'
b0 &
1%
0$
1#
0"
b0 !
$end
#10
1"
1$
#20
1)
1(
b1000 !
b1000 &
0"
0$
0#
0%
#30
1"
1$
#40
1,
1+
0)
0(
b100 !
b100 &
0"
0$
#50
1"
1$
#60
1)
1(
b1100 !
b1100 &
0"
0$
#70
1"
1$
#80
1/
1.
0,
0+
0)
0(
b10 !
b10 &
0"
0$
#90
1"
1$
#100
1)
1(
b1010 !
b1010 &
0"
0$
#110
1"
1$
#120
1,
1+
0)
0(
b110 !
b110 &
0"
0$
#130
1"
1$
#140
1)
1(
b1110 !
b1110 &
0"
0$
#150
1"
1$
#160
11
0/
0.
0,
0+
0)
0(
b1 !
b1 &
0"
0$
#170
1"
1$
#180
1)
1(
b1001 !
b1001 &
0"
0$
