SEM-3/Verilog-Codes/lab9/clock5.v
module dff(d,clk,reset,q);
input d,clk,reset;
output reg q;
always @(posedge clk or posedge reset)
begin
  if(reset) q<=0;
  else q<=d;
end
endmodule 

module clock5(clk,reset,a,y);
input clk,reset;
output y;
output [2:0]a;
dff stg0(((a[2]&~a[0])|(a[2]&~a[1])|(~a[2]&a[1]&a[0])),clk,reset,a[2]);
dff stg1((a[1]^a[0]),clk,reset,a[1]);
dff stg2((~a[0]),clk,reset,a[0]);
assign y = a[2]&~a[1]&~a[0];
endmodule

SEM-3/Verilog-Codes/lab9/clock5_tb.v
`timescale 1ns/1ns
`include "clock5.v"
module clock5_tb;
reg clk,reset;
wire y;
wire [2:0]a;
clock5 uut(clk,reset,a,y);
initial begin
  $dumpfile("clock5_tb.vcd");
  $dumpvars(0,clock5_tb);
  clk=0;
  forever #20 clk=~clk;
end
initial begin
  reset=1; #20;
  reset=0; #200;
  $display("Test complete");
  $finish;
end
endmodule

SEM-3/Verilog-Codes/lab9/clock5_tb.vcd
$date
	Tue Nov 21 20:18:38 2023
$end
$version
	Icarus Verilog
$end
$timescale
	1ns
$end
$scope module clock5_tb $end
$var wire 3 ! a [2:0] $end
$var wire 1 " y $end
$var reg 1 # clk $end
$var reg 1 $ reset $end
$scope module uut $end
$var wire 3 % a [2:0] $end
$var wire 1 & clk $end
$var wire 1 ' reset $end
$var wire 1 " y $end
$scope module stg0 $end
$var wire 1 & clk $end
$var wire 1 ( d $end
$var wire 1 ' reset $end
$var reg 1 ) q $end
$upscope $end
$scope module stg1 $end
$var wire 1 & clk $end
$var wire 1 * d $end
$var wire 1 ' reset $end
$var reg 1 + q $end
$upscope $end
$scope module stg2 $end
$var wire 1 & clk $end
$var wire 1 , d $end
$var wire 1 ' reset $end
$var reg 1 - q $end
$upscope $end
$upscope $end
$upscope $end
$enddefinitions $end
#0
$dumpvars
0-
1,
0+
0*
0)
0(
1'
0&
b0 %
1$
0#
0"
b0 !
$end
#20
1*
0,
1-
b1 !
b1 %
0$
0'
1#
1&
#40
0#
0&
#60
1,
1+
0-
b10 !
b10 %
1#
1&
#80
0#
0&
#100
1(
0*
0,
1-
b11 !
b11 %
1#
1&
#120
0#
0&
#140
1(
1"
1,
1)
0+
0-
b100 !
b100 %
1#
1&
#160
0#
0&
#180
0"
1*
0,
1-
b101 !
b101 %
1#
1&
#200
0#
0&
#220
0"
1,
1+
0-
b110 !
b110 %
1#
1&
#240
0#
0&
#260
0(
0*
0,
1-
b111 !
b111 %
1#
1&
#280
0#
0&
#300
1,
0)
0+
0-
b0 !
b0 %
1#
1&
#320
0#
0&
#340
1*
0,
1-
b1 !
b1 %
1#
1&
#360
0#
0&
#380
1,
1+
0-
b10 !
b10 %
1#
1&
#400
0#
0&
#420
1(
0*
0,
1-
b11 !
b11 %
1#
1&
#440
0#
0&
#460
1(
1"
1,
1)
0+
0-
b100 !
b100 %
1#
1&
#480
0#
0&
#500
0"
1*
0,
1-
b101 !
b101 %
1#
1&
#520
0#
0&
#540
0"
1,
1+
0-
b110 !
b110 %
1#
1&
#560
0#
0&
#580
0(
0*
0,
1-
b111 !
b111 %
1#
1&
#600
0#
0&
#620
1,
0)
0+
0-
b0 !
b0 %
1#
1&
#640
0#
0&
#660
1*
0,
1-
b1 !
b1 %
1#
1&
#680
0#
0&
#700
1,
1+
0-
b10 !
b10 %
1#
1&
#720
0#
0&
#740
1(
0*
0,
1-
b11 !
b11 %
1#
1&
#760
0#
0&
#780
1(
1"
1,
1)
0+
0-
b100 !
b100 %
1#
1&
#800
0#
0&
#820
0"
1*
0,
1-
b101 !
b101 %
1#
1&
