SEM-3/Verilog-Codes/lab9/ring.v
module dff(inp,d,clk,reset,q);
input inp,d,clk,reset;
output reg q;
always @(posedge clk or posedge reset)
begin
  if(reset) q<=inp;
  else q<=d;
end
endmodule

module ring(clk,reset,q);
input clk,reset;
output [3:0]q;
dff stg0(1'b1,q[0],clk,reset,q[3]);
dff stg1(1'b0,q[3],clk,reset,q[2]);
dff stg2(1'b0,q[2],clk,reset,q[1]);
dff stg3(1'b0,q[1],clk,reset,q[0]);
endmodule

//BEHAVIOURAL CODE
// module ring(clk,reset,q);
// input clk,reset;
// output reg [3:0]q;
// always @(posedge clk or posedge reset)
// begin if(reset)q<=4'b1000;
//   else q<={q[0],q[3:1]};
// end
// endmodule

//2 BIT COUNTER AND DECODER
// module tff(t,clk,reset,q);
// input t,clk,reset;
// output reg q;
// always @(posedge clk or posedge reset)
// begin
//   if(reset) q<=1'b0;
//   else
//     begin
//       if(t==1'b0) q<=q;
//       else q<=~q;
//     end
// end
// endmodule


// module dec2to4(en,w,y);
// input en;
// input [1:0]w;
// output reg [0:3]y;
// always @(en,w)
// begin
//   if(en==1)
//     begin
//       if(w==0) y = 4'b1000;
//       else if(w==1) y = 4'b0100;
//       else if(w==2) y = 4'b0010;
//       else if(w==3) y = 4'b0001;
//     end
//   else y= 4'b0000;
// end
// endmodule

// module ring(clk,reset,q);
// input clk,reset;
// output [3:0]q;
// wire [1:0]a;
// tff stg0(a[0],clk,reset,a[1]);
// tff stg1(1'b1,clk,reset,a[0]);
// dec2to4 stg2(1'b1,a,q);
// endmodule

SEM-3/Verilog-Codes/lab9/ring_tb.v
`timescale 1ns/1ns
`include "ring.v"
module ring_tb;
reg clk,reset;
wire [3:0]q;
ring uut(clk,reset,q);
initial begin
  $dumpfile("ring_tb.vcd");
  $dumpvars(0,ring_tb);
  clk=0;
  forever #10 clk=~clk;
end
initial begin
  reset=1; #20
  reset=0; #160
  $display("Test complete");
  $finish;
end
endmodule

SEM-3/Verilog-Codes/lab9/ring_tb.vcd
$date
	Tue Nov 21 19:52:57 2023
$end
$version
	Icarus Verilog
$end
$timescale
	1ns
$end
$scope module ring_tb $end
$var wire 4 ! q [3:0] $end
$var reg 1 " clk $end
$var reg 1 # reset $end
$scope module uut $end
$var wire 1 $ clk $end
$var wire 4 % q [3:0] $end
$var wire 1 & reset $end
$scope module stg0 $end
$var wire 1 $ clk $end
$var wire 1 ' d $end
$var wire 1 ( inp $end
$var wire 1 & reset $end
$var reg 1 ) q $end
$upscope $end
$scope module stg1 $end
$var wire 1 $ clk $end
$var wire 1 * d $end
$var wire 1 + inp $end
$var wire 1 & reset $end
$var reg 1 , q $end
$upscope $end
$scope module stg2 $end
$var wire 1 $ clk $end
$var wire 1 - d $end
$var wire 1 . inp $end
$var wire 1 & reset $end
$var reg 1 / q $end
$upscope $end
$scope module stg3 $end
$var wire 1 $ clk $end
$var wire 1 0 d $end
$var wire 1 1 inp $end
$var wire 1 & reset $end
$var reg 1 2 q $end
$upscope $end
$upscope $end
$upscope $end
$enddefinitions $end
#0
$dumpvars
02
01
00
0/
0.
0-
0,
0+
1*
1)
1(
0'
1&
b1000 %
0$
1#
0"
b1000 !
$end
#10
1"
1$
#20
0"
0$
0#
0&
#30
0*
1-
0)
1,
b100 !
b100 %
1"
1$
#40
0"
0$
#50
10
0-
1/
0,
b10 !
b10 %
1"
1$
#60
0"
0$
#70
00
1'
0/
12
b1 !
b1 %
1"
1$
#80
0"
0$
#90
0'
1*
02
1)
b1000 !
b1000 %
1"
1$
#100
0"
0$
#110
0*
1-
0)
1,
b100 !
b100 %
1"
1$
#120
0"
0$
#130
10
0-
1/
0,
b10 !
b10 %
1"
1$
#140
0"
0$
#150
00
1'
0/
12
b1 !
b1 %
1"
1$
#160
0"
0$
#170
0'
1*
02
1)
b1000 !
b1000 %
1"
1$
