SEM-3/Verilog-Codes/lab1/f2.v
module f2(a,b,c,f);
input a,b,c;
output f;
assign f = (a|~b|c)&(a|b|~c)&(~a|b|~c);
endmodule

SEM-3/Verilog-Codes/lab1/f2_tb.v
`timescale 1ns/1ns
`include "f2.v"
module f2_tb;
reg a,b,c;
wire f;
f2 uut(a,b,c,f);
initial begin
  $dumpfile("f2_tb.vcd");
  $dumpvars(0,f2_tb);
  a=0; b=0; c=0; #20
  a=0; b=0; c=1; #20
  a=0; b=1; c=0; #20
  a=0; b=1; c=1; #20
  a=1; b=0; c=0; #20
  a=1; b=0; c=1; #20
  a=1; b=1; c=0; #20
  a=1; b=1; c=1; #20
  $display("Test complete");
end
endmodule

SEM-3/Verilog-Codes/lab1/f2_tb.vcd
$date
	Sat Nov 18 11:49:42 2023
$end
$version
	Icarus Verilog
$end
$timescale
	1ns
$end
$scope module f2_tb $end
$var wire 1 ! f $end
$var reg 1 " a $end
$var reg 1 # b $end
$var reg 1 $ c $end
$scope module uut $end
$var wire 1 % a $end
$var wire 1 & b $end
$var wire 1 ' c $end
$var wire 1 ! f $end
$upscope $end
$upscope $end
$enddefinitions $end
#0
$dumpvars
0'
0&
0%
0$
0#
0"
1!
$end
#20
0!
1$
1'
#40
0!
0$
0'
1#
1&
#60
1!
1$
1'
#80
0$
0'
0#
0&
1"
1%
#100
0!
1$
1'
#120
1!
0$
0'
1#
1&
#140
1$
1'
