SEM-3/Verilog-Codes/lab1/input4.v
module input4(x1,x2,x3,x4,f);
input x1,x2,x3,x4;
output f;
assign f = (~x1&x2&x3&x4)|(x1&~x2&x3&x4)|(x1&x2&~x3&x4)|(x1&x2&x3&~x4)|(x1&x2&x3&x4);
endmodule

SEM-3/Verilog-Codes/lab1/input4_tb.v
`timescale 1ns/1ns
`include "input4.v"
module input4_tb;
reg x1,x2,x3,x4;
wire f;
input4 uut(x1,x2,x3,x4,f);
initial begin
  $dumpfile("input4_tb.vcd");
  $dumpvars(0,input4_tb);
  x1=0; x2=0; x3=0; x4=0; #20
  x1=0; x2=0; x3=0; x4=1; #20
  x1=0; x2=0; x3=1; x4=0; #20
  x1=0; x2=0; x3=1; x4=1; #20
  x1=0; x2=1; x3=0; x4=0; #20
  x1=0; x2=1; x3=0; x4=1; #20
  x1=0; x2=1; x3=1; x4=0; #20
  x1=0; x2=1; x3=1; x4=1; #20
  x1=1; x2=0; x3=0; x4=0; #20
  x1=1; x2=0; x3=0; x4=1; #20
  x1=1; x2=0; x3=1; x4=0; #20
  x1=1; x2=0; x3=1; x4=1; #20
  x1=1; x2=1; x3=0; x4=0; #20
  x1=1; x2=1; x3=0; x4=1; #20
  x1=1; x2=1; x3=1; x4=0; #20
  x1=1; x2=1; x3=1; x4=1; #20
  $display("Test complete");
end
endmodule

SEM-3/Verilog-Codes/lab1/input4_tb.vcd
$date
	Sat Nov 18 12:02:15 2023
$end
$version
	Icarus Verilog
$end
$timescale
	1ns
$end
$scope module input4_tb $end
$var wire 1 ! f $end
$var reg 1 " x1 $end
$var reg 1 # x2 $end
$var reg 1 $ x3 $end
$var reg 1 % x4 $end
$scope module uut $end
$var wire 1 ! f $end
$var wire 1 & x1 $end
$var wire 1 ' x2 $end
$var wire 1 ( x3 $end
$var wire 1 ) x4 $end
$upscope $end
$upscope $end
$enddefinitions $end
#0
$dumpvars
0)
0(
0'
0&
0%
0$
0#
0"
0!
$end
#20
1%
1)
#40
0%
0)
1$
1(
#60
1%
1)
#80
0%
0)
0$
0(
1#
1'
#100
1%
1)
#120
0%
0)
1$
1(
#140
1!
1%
1)
#160
0!
0%
0)
0$
0(
0#
0'
1"
1&
#180
1%
1)
#200
0%
0)
1$
1(
#220
1!
1%
1)
#240
0!
0%
0)
0$
0(
1#
1'
#260
1!
1%
1)
#280
0%
0)
1$
1(
#300
1%
1)
