SEM-3/Verilog-Codes/lab1/kmap1.v
module kmap1(a,b,c,d,f);
input a,b,c,d;
output f;
assign f = c | (a & d);
endmodule

SEM-3/Verilog-Codes/lab1/kmap1_tb.v
`timescale 1ns/1ns
`include "kmap1.v"
module kmap1_tb;
reg a,b,c,d;
wire f;
kmap1 uut(a,b,c,d,f);
initial begin
  $dumpfile("kmap1_tb.vcd");
  $dumpvars(0,kmap1_tb);
  a=0; b=0; c=0; d=0; #20
  a=0; b=0; c=0; d=1; #20
  a=0; b=0; c=1; d=0; #20
  a=0; b=0; c=1; d=1; #20
  a=0; b=1; c=0; d=0; #20
  a=0; b=1; c=0; d=1; #20
  a=0; b=1; c=1; d=0; #20
  a=0; b=1; c=1; d=1; #20
  a=1; b=0; c=0; d=0; #20
  a=1; b=0; c=0; d=1; #20
  a=1; b=0; c=1; d=0; #20
  a=1; b=0; c=1; d=1; #20
  a=1; b=1; c=0; d=0; #20
  a=1; b=1; c=0; d=1; #20
  a=1; b=1; c=1; d=0; #20
  a=1; b=1; c=1; d=1; #20
  $display("Test complete");
end
endmodule

SEM-3/Verilog-Codes/lab1/kmap1_tb.vcd
$date
	Sat Nov 18 11:17:56 2023
$end
$version
	Icarus Verilog
$end
$timescale
	1ns
$end
$scope module kmap1_tb $end
$var wire 1 ! f $end
$var reg 1 " a $end
$var reg 1 # b $end
$var reg 1 $ c $end
$var reg 1 % d $end
$scope module uut $end
$var wire 1 & a $end
$var wire 1 ' b $end
$var wire 1 ( c $end
$var wire 1 ) d $end
$var wire 1 ! f $end
$upscope $end
$upscope $end
$enddefinitions $end
#0
$dumpvars
0)
0(
0'
0&
0%
0$
0#
0"
0!
$end
#20
1%
1)
#40
1!
0%
0)
1$
1(
#60
1%
1)
#80
0!
0%
0)
0$
0(
1#
1'
#100
1%
1)
#120
1!
0%
0)
1$
1(
#140
1%
1)
#160
0!
0%
0)
0$
0(
0#
0'
1"
1&
#180
1!
1%
1)
#200
0%
0)
1$
1(
#220
1%
1)
#240
0!
0%
0)
0$
0(
1#
1'
#260
1!
1%
1)
#280
0%
0)
1$
1(
#300
1%
1)
