SEM-3/Verilog-Codes/lab1/kmap4.v
module kmap4(a,b,c,d,f);
input a,b,c,d;
output f;
assign f = (~c | d) & (~a | d) & (a | ~b | c | ~d);
endmodule

SEM-3/Verilog-Codes/lab1/kmap4_tb.v
`timescale 1ns/1ns
`include "kmap4.v"
module kmap4_tb;
reg a,b,c,d;
wire f;
kmap4 uut(a,b,c,d,f);
initial begin
  $dumpfile("kmap4_tb.vcd");
  $dumpvars(0,kmap4_tb);
  a=0; b=0; c=0; d=0; #20
  a=0; b=0; c=0; d=1; #20
  a=0; b=0; c=1; d=0; #20
  a=0; b=0; c=1; d=1; #20
  a=0; b=1; c=0; d=0; #20
  a=0; b=1; c=0; d=1; #20
  a=0; b=1; c=1; d=0; #20
  a=0; b=1; c=1; d=1; #20
  a=1; b=0; c=0; d=0; #20
  a=1; b=0; c=0; d=1; #20
  a=1; b=0; c=1; d=0; #20
  a=1; b=0; c=1; d=1; #20
  a=1; b=1; c=0; d=0; #20
  a=1; b=1; c=0; d=1; #20
  a=1; b=1; c=1; d=0; #20
  a=1; b=1; c=1; d=1; #20
  $display("Test complete");
end
endmodule

SEM-3/Verilog-Codes/lab1/kmap4_tb.vcd
$date
	Sat Nov 18 11:36:56 2023
$end
$version
	Icarus Verilog
$end
$timescale
	1ns
$end
$scope module kmap4_tb $end
$var wire 1 ! f $end
$var reg 1 " a $end
$var reg 1 # b $end
$var reg 1 $ c $end
$var reg 1 % d $end
$scope module uut $end
$var wire 1 & a $end
$var wire 1 ' b $end
$var wire 1 ( c $end
$var wire 1 ) d $end
$var wire 1 ! f $end
$upscope $end
$upscope $end
$enddefinitions $end
#0
$dumpvars
0)
0(
0'
0&
0%
0$
0#
0"
1!
$end
#20
1%
1)
#40
0!
0%
0)
1$
1(
#60
1!
1%
1)
#80
0%
0)
0$
0(
1#
1'
#100
0!
1%
1)
#120
0%
0)
1$
1(
#140
1!
1%
1)
#160
0!
0%
0)
0$
0(
0#
0'
1"
1&
#180
1!
1%
1)
#200
0!
0%
0)
1$
1(
#220
1!
1%
1)
#240
0!
0%
0)
0$
0(
1#
1'
#260
1!
1%
1)
#280
0!
0%
0)
1$
1(
#300
1!
1%
1)
