SEM-3/Verilog-Codes/lab2/fd.v
module fd(a,b,c,d,f);
input a,b,c,d;
output f;
assign g = c^d;
assign f = (a&g) | (b&~g);
endmodule

SEM-3/Verilog-Codes/lab2/fd_tb.v
`timescale 1ns/1ns
`include "fd.v"
module fd_tb;
reg a,b,c,d;
wire f;
fd uut(a,b,c,d,f);
initial begin
  $dumpfile("fd_tb.vcd");
  $dumpvars(0,fd_tb);
  a=0; b=0; c=0; d=0; #20
  a=0; b=0; c=0; d=1; #20
  a=0; b=0; c=1; d=0; #20
  a=0; b=0; c=1; d=1; #20
  a=0; b=1; c=0; d=0; #20
  a=0; b=1; c=0; d=1; #20
  a=0; b=1; c=1; d=0; #20
  a=0; b=1; c=1; d=1; #20
  a=1; b=0; c=0; d=0; #20
  a=1; b=0; c=0; d=1; #20
  a=1; b=0; c=1; d=0; #20
  a=1; b=0; c=1; d=1; #20
  a=1; b=1; c=0; d=0; #20
  a=1; b=1; c=0; d=1; #20
  a=1; b=1; c=1; d=0; #20
  a=1; b=1; c=1; d=1; #20
  $display("Test complete");
end
endmodule

SEM-3/Verilog-Codes/lab2/fd_tb.vcd
$date
	Sat Nov 18 12:25:23 2023
$end
$version
	Icarus Verilog
$end
$timescale
	1ns
$end
$scope module fd_tb $end
$var wire 1 ! f $end
$var reg 1 " a $end
$var reg 1 # b $end
$var reg 1 $ c $end
$var reg 1 % d $end
$scope module uut $end
$var wire 1 & a $end
$var wire 1 ' b $end
$var wire 1 ( c $end
$var wire 1 ) d $end
$var wire 1 ! f $end
$var wire 1 * g $end
$upscope $end
$upscope $end
$enddefinitions $end
#0
$dumpvars
0*
0)
0(
0'
0&
0%
0$
0#
0"
0!
$end
#20
1*
1%
1)
#40
0%
0)
1$
1(
#60
0*
1%
1)
#80
1!
0%
0)
0$
0(
1#
1'
#100
0!
1*
1%
1)
#120
0%
0)
1$
1(
#140
1!
0*
1%
1)
#160
0!
0%
0)
0$
0(
0#
0'
1"
1&
#180
1!
1*
1%
1)
#200
0%
0)
1$
1(
#220
0!
0*
1%
1)
#240
1!
0%
0)
0$
0(
1#
1'
#260
1*
1%
1)
#280
0%
0)
1$
1(
#300
0*
1%
1)
