SEM-3/Verilog-Codes/lab2/fullAdder.v
module fullAdder(cin,x,y,cout,s);
input cin,x,y;
output cout,s;
assign cout = (x&y)|(y&cin)|(x&cin);
assign s = x^y^cin;
endmodule

SEM-3/Verilog-Codes/lab2/fullAdder_tb.v
`timescale 1ns/1ns
`include "fullAdder.v"
module fullAdder_tb;
reg cin,x,y;
wire cout,s;
fullAdder uut(cin,x,y,cout,s);
initial begin
  $dumpfile("fullAdder_tb.vcd");
  $dumpvars(0,fullAdder_tb);
  cin=0; x=0; y=0; #20;
  cin=0; x=0; y=1; #20;
  cin=0; x=1; y=0; #20;
  cin=0; x=1; y=1; #20;
  cin=1; x=0; y=0; #20;
  cin=1; x=0; y=1; #20;
  cin=1; x=1; y=0; #20;
  cin=1; x=1; y=1; #20;
  $display("Test complete");
end
endmodule

SEM-3/Verilog-Codes/lab2/fullAdder_tb.vcd
$date
	Sat Nov 18 12:35:47 2023
$end
$version
	Icarus Verilog
$end
$timescale
	1ns
$end
$scope module fullAdder_tb $end
$var wire 1 ! cout $end
$var wire 1 " s $end
$var reg 1 # cin $end
$var reg 1 $ x $end
$var reg 1 % y $end
$scope module uut $end
$var wire 1 & cin $end
$var wire 1 ! cout $end
$var wire 1 " s $end
$var wire 1 ' x $end
$var wire 1 ( y $end
$upscope $end
$upscope $end
$enddefinitions $end
#0
$dumpvars
0(
0'
0&
0%
0$
0#
0"
0!
$end
#20
1"
1%
1(
#40
0%
0(
1$
1'
#60
1!
0"
1%
1(
#80
0!
1"
0%
0(
0$
0'
1#
1&
#100
1!
0"
1%
1(
#120
0%
0(
1$
1'
#140
1"
1%
1(
