SEM-3/Verilog-Codes/lab10/counterjk.v
module jkff(j,k,clk,reset,q);
input j,k,clk,reset;
output reg q;
always @(posedge clk or posedge reset)
  begin
    if(reset)q<=0;
    else
      begin
        if(j==0 && k==0) q<=q;
        else if (j==0 && k==1) q<=0;
        else if (j==1 && k==0) q<=1;
        else if (j==1 && k==1) q<=~q;
      end
  end
endmodule

module counterjk(clk,reset,w);
input clk,reset;
output [2:0]w;
jkff stg0(w[1],(w[1]&w[0]),clk,reset,w[2]); 
jkff stg1(w[0],(w[0]|~w[2]),clk,reset,w[1]); 
jkff stg2((w[2]|~w[1]),1'b1,clk,reset,w[0]);
endmodule

SEM-3/Verilog-Codes/lab10/counterjk_tb.v
`timescale 1ns/1ns
`include "counterjk.v"
module counterjk_tb;
reg clk,reset;
wire [2:0]w;
counterjk uut(clk,reset,w);
initial begin
  $dumpfile("counterjk_tb.vcd");
  $dumpvars(0,counterjk_tb);
  clk=0;
  forever #10 clk=~clk;
end
initial begin
  reset=1; #20;
  reset=0; #160;
  $display("Test complete");
  $finish;
end
endmodule

SEM-3/Verilog-Codes/lab10/counterjk_tb.vcd
$date
	Tue Nov 21 13:29:44 2023
$end
$version
	Icarus Verilog
$end
$timescale
	1ns
$end
$scope module counterjk_tb $end
$var wire 3 ! w [2:0] $end
$var reg 1 " clk $end
$var reg 1 # reset $end
$scope module uut $end
$var wire 1 $ clk $end
$var wire 1 % reset $end
$var wire 3 & w [2:0] $end
$scope module stg0 $end
$var wire 1 $ clk $end
$var wire 1 ' j $end
$var wire 1 ( k $end
$var wire 1 % reset $end
$var reg 1 ) q $end
$upscope $end
$scope module stg1 $end
$var wire 1 $ clk $end
$var wire 1 * j $end
$var wire 1 + k $end
$var wire 1 % reset $end
$var reg 1 , q $end
$upscope $end
$scope module stg2 $end
$var wire 1 $ clk $end
$var wire 1 - j $end
$var wire 1 . k $end
$var wire 1 % reset $end
$var reg 1 / q $end
$upscope $end
$upscope $end
$upscope $end
$enddefinitions $end
#0
$dumpvars
0/
1.
1-
0,
1+
0*
0)
0(
0'
b0 &
1%
0$
1#
0"
b0 !
$end
#10
1"
1$
#20
0"
0$
0#
0%
#30
1*
1/
b1 !
b1 &
1"
1$
#40
0"
0$
#50
0-
0*
1'
0/
1,
b10 !
b10 &
1"
1$
#60
0"
0$
#70
0+
1-
0'
1)
0,
b100 !
b100 &
1"
1$
#80
0"
0$
#90
1+
1*
1/
b101 !
b101 &
1"
1$
#100
0"
0$
#110
0+
1'
0*
1,
0/
b110 !
b110 &
1"
1$
#120
0"
0$
#130
1(
1+
1*
1/
b111 !
b111 &
1"
1$
#140
0"
0$
#150
0(
1+
0'
0*
0)
0,
0/
b0 !
b0 &
1"
1$
#160
0"
0$
#170
1*
1/
b1 !
b1 &
1"
1$
