SEM-3/Verilog-Codes/lab10/csr.v
module srff(s,r,clk,reset,q);
input s,r,clk,reset;
output reg q;
always @(posedge clk or posedge reset)
begin
  if(reset) q<=0;
  else
    begin
      if(s==0 && r==0) q<=q;
      else if(s==0 && r==1) q<=0;
      else if (s==1 && r==0) q<=1;
    end
end
endmodule

module csr(clk,reset,w);
input clk,reset;
output [2:0]w;
srff stg0((~w[1]&~w[0]),(w[2]&~w[1]),clk,reset,w[2]);
srff stg1((~w[2]&~w[1]),((w[2]&~w[0])|(~w[2]&w[1]&w[0])),clk,reset,w[1]);
srff stg2(~w[0],((~w[2]&w[0])|(w[1]&w[0])),clk,reset,w[0]);
endmodule

SEM-3/Verilog-Codes/lab10/csr_tb.v
`timescale 1ns/1ns
`include "csr.v"
module csr_tb;
reg clk,reset;
wire [2:0]w;
csr uut(clk,reset,w);
initial begin
  $dumpfile("csr_tb.vcd");
  $dumpvars(0,csr_tb);
  clk=0;
  forever #10 clk=~clk;
end
initial begin
  reset=1; #20;
  reset=0; #160;
  $display("Test complete");
  $finish;
end
endmodule

SEM-3/Verilog-Codes/lab10/csr_tb.vcd
$date
	Tue Nov 21 15:08:37 2023
$end
$version
	Icarus Verilog
$end
$timescale
	1ns
$end
$scope module csr_tb $end
$var wire 3 ! w [2:0] $end
$var reg 1 " clk $end
$var reg 1 # reset $end
$scope module uut $end
$var wire 1 $ clk $end
$var wire 1 % reset $end
$var wire 3 & w [2:0] $end
$scope module stg0 $end
$var wire 1 $ clk $end
$var wire 1 ' r $end
$var wire 1 % reset $end
$var wire 1 ( s $end
$var reg 1 ) q $end
$upscope $end
$scope module stg1 $end
$var wire 1 $ clk $end
$var wire 1 * r $end
$var wire 1 % reset $end
$var wire 1 + s $end
$var reg 1 , q $end
$upscope $end
$scope module stg2 $end
$var wire 1 $ clk $end
$var wire 1 - r $end
$var wire 1 % reset $end
$var wire 1 . s $end
$var reg 1 / q $end
$upscope $end
$upscope $end
$upscope $end
$enddefinitions $end
#0
$dumpvars
0/
1.
0-
0,
1+
0*
0)
1(
0'
b0 &
1%
0$
1#
0"
b0 !
$end
#10
1"
1$
#20
0"
0$
0#
0%
#30
0*
0+
0(
1-
0.
1)
1,
1/
b111 !
b111 &
1"
1$
#40
0"
0$
#50
1*
0-
1.
0/
b110 !
b110 &
1"
1$
#60
0"
0$
#70
0*
1'
0.
0,
1/
b101 !
b101 &
1"
1$
#80
0"
0$
#90
1-
1+
0'
0)
b1 !
b1 &
1"
1$
#100
0"
0$
#110
0+
0-
1.
1,
0/
b10 !
b10 &
1"
1$
#120
0"
0$
#130
1*
1-
0.
1/
b11 !
b11 &
1"
1$
#140
0"
0$
#150
1+
1(
0*
0-
1.
0,
0/
b0 !
b0 &
1"
1$
#160
0"
0$
#170
0(
1-
0+
0*
0.
0'
1/
1,
1)
b111 !
b111 &
1"
1$
