SEM-3/Verilog-Codes/lab10/last.v
module tff(t,clk,reset,q);
input t,clk,reset;
output reg q;
always @(posedge clk or posedge reset)
begin
  if(reset) q<=0;
  else
    begin
      if(t==0) q<=q;
      else q<=~q;
    end
end
endmodule

module last(x,clk,reset,w);
input x,clk,reset;
output [2:0]w;
tff stg0(((w[0]&~x)|(~w[1]&x)|(w[2]&w[1]&~x)),clk,reset,w[2]);
tff stg1(((w[0]&~x)|(~w[0]&x)|(w[2])|(~w[1])),clk,reset,w[1]);
tff stg2(((w[0])|(w[2]&~w[1]&x)|(~w[2]&w[1]&~x)),clk,reset,w[0]);
endmodule

SEM-3/Verilog-Codes/lab10/last_tb.v
`timescale 1ns/1ns
`include "last.v"
module last_tb;
reg x,clk,reset;
wire [2:0]w;
last uut(x,clk,reset,w);
initial begin
  $dumpfile("last_tb.vcd");
  $dumpvars(0,last_tb);
  clk=0;
  forever #10 clk=~clk;
end
initial begin
  x=0; reset=1; #20;
  x=1; reset=0; #20;
  x=0; reset=0; #20;
  x=1; reset=0; #20;
  x=0; reset=0; #20;
  x=1; reset=0; #20;
  x=0; reset=0; #20;
  $display("Test complete");
  $finish;
end
endmodule

SEM-3/Verilog-Codes/lab10/last_tb.vcd
$date
	Tue Nov 21 16:07:39 2023
$end
$version
	Icarus Verilog
$end
$timescale
	1ns
$end
$scope module last_tb $end
$var wire 3 ! w [2:0] $end
$var reg 1 " clk $end
$var reg 1 # reset $end
$var reg 1 $ x $end
$scope module uut $end
$var wire 1 % clk $end
$var wire 1 & reset $end
$var wire 3 ' w [2:0] $end
$var wire 1 ( x $end
$scope module stg0 $end
$var wire 1 % clk $end
$var wire 1 & reset $end
$var wire 1 ) t $end
$var reg 1 * q $end
$upscope $end
$scope module stg1 $end
$var wire 1 % clk $end
$var wire 1 & reset $end
$var wire 1 + t $end
$var reg 1 , q $end
$upscope $end
$scope module stg2 $end
$var wire 1 % clk $end
$var wire 1 & reset $end
$var wire 1 - t $end
$var reg 1 . q $end
$upscope $end
$upscope $end
$upscope $end
$enddefinitions $end
#0
$dumpvars
0.
0-
0,
1+
0*
0)
0(
b0 '
1&
0%
0$
1#
0"
b0 !
$end
#10
1"
1%
#20
1)
0"
0%
0#
0&
1$
1(
#30
0)
1*
1,
b110 !
b110 '
1"
1%
#40
1)
0"
0%
0$
0(
#50
0)
0,
0*
b0 !
b0 '
1"
1%
#60
1)
0"
0%
1$
1(
#70
0)
1*
1,
b110 !
b110 '
1"
1%
#80
1)
0"
0%
0$
0(
#90
0)
0,
0*
b0 !
b0 '
1"
1%
#100
1)
0"
0%
1$
1(
#110
0)
1*
1,
b110 !
b110 '
1"
1%
#120
1)
0"
0%
0$
0(
#130
0)
0,
0*
b0 !
b0 '
1"
1%
