SEM-3/Verilog-Codes/lab7/nbit.v
module nbit(i,clk,o);
parameter n = 4;
input [n-1:0]i;
input clk;
output reg [n-1:0]o;
always @(posedge clk)
begin
  o<=i;
end
endmodule

SEM-3/Verilog-Codes/lab7/nbit_tb.v
`timescale 1ns/1ns
`include "nbit.v"
module nbit_tb;
reg [3:0]i;
reg clk;
wire [3:0]o;
nbit uut(i,clk,o);
initial begin
  $dumpfile("nbit_tb.vcd");
  $dumpvars(0,nbit_tb);
  clk=1'b0;
  forever #10 clk=~clk;
end
initial begin
  i=4'b1000; #20;
  i=4'b0111; #20;
  i=4'b1101; #20;
  i=4'b0101; #20;
  $display("Test complete");
  $finish;
end
endmodule

SEM-3/Verilog-Codes/lab7/nbit_tb.vcd
$date
	Sun Nov 19 09:39:30 2023
$end
$version
	Icarus Verilog
$end
$timescale
	1ns
$end
$scope module nbit_tb $end
$var wire 4 ! o [3:0] $end
$var reg 1 " clk $end
$var reg 4 # i [3:0] $end
$scope module uut $end
$var wire 1 $ clk $end
$var wire 4 % i [3:0] $end
$var reg 4 & o [3:0] $end
$upscope $end
$upscope $end
$enddefinitions $end
#0
$dumpvars
bx &
b1000 %
0$
b1000 #
0"
bx !
$end
#10
b1000 &
b1000 !
1"
1$
#20
0"
0$
b111 #
b111 %
#30
b111 &
b111 !
1"
1$
#40
0"
0$
b1101 #
b1101 %
#50
b1101 &
b1101 !
1"
1$
#60
0"
0$
b101 #
b101 %
#70
b101 &
b101 !
1"
1$
