SEM-3/Verilog-Codes/lab8/l8q1.v
module dff(d,clk,reset,q);
input d,clk,reset;
output reg q;
always @(posedge clk or posedge reset)
begin
if(reset) q<=1'b0;
else q<=d;
end
endmodule

module l8q1(x,clk,reset,y,a);
input x,clk,reset;
output y;
output [3:1]a;
dff stg0(((a[3]&~x)|(a[2]&~a[1]&~x)),clk,reset,a[3]);
dff stg1(((a[3]&x)|(~a[3]&~a[2]&~x)|(a[1]&~x)),clk,reset,a[2]);
dff stg2(((a[2]&a[1])|(~a[3]&~a[2]&~a[1])),clk,reset,a[1]);
assign y = (a[2]&~x)|(a[3]&x)|(a[2]&a[1]);
endmodule

SEM-3/Verilog-Codes/lab8/l8q1_tb.v
`timescale 1ns/1ns
`include "l8q1.v"
module l8q1_tb;
reg x,clk,reset;
wire y;
wire [3:1]a;
l8q1 uut(x,clk,reset,y,a);
initial begin
  $dumpfile("l8q1_tb.vcd");
  $dumpvars(0,l8q1_tb);
  clk=1'b0;
  forever #10 clk=~clk;
end
initial begin
  x=1'b1; reset=1'b1; #20;
  x=1'b0; reset=1'b0; #20;
  x=1'b1; #20;
  x=1'b0; #20;
  x=1'b1; #20;
  x=1'b0; #20;
  x=1'b1; #20;
  $display("Test complete");
  $finish;
end
endmodule

SEM-3/Verilog-Codes/lab8/l8q1_tb.vcd
$date
	Wed Nov 22 10:36:29 2023
$end
$version
	Icarus Verilog
$end
$timescale
	1ns
$end
$scope module l8q1_tb $end
$var wire 3 ! a [3:1] $end
$var wire 1 " y $end
$var reg 1 # clk $end
$var reg 1 $ reset $end
$var reg 1 % x $end
$scope module uut $end
$var wire 3 & a [3:1] $end
$var wire 1 ' clk $end
$var wire 1 ( reset $end
$var wire 1 ) x $end
$var wire 1 " y $end
$scope module stg0 $end
$var wire 1 ' clk $end
$var wire 1 * d $end
$var wire 1 ( reset $end
$var reg 1 + q $end
$upscope $end
$scope module stg1 $end
$var wire 1 ' clk $end
$var wire 1 , d $end
$var wire 1 ( reset $end
$var reg 1 - q $end
$upscope $end
$scope module stg2 $end
$var wire 1 ' clk $end
$var wire 1 . d $end
$var wire 1 ( reset $end
$var reg 1 / q $end
$upscope $end
$upscope $end
$upscope $end
$enddefinitions $end
#0
$dumpvars
0/
1.
0-
0,
0+
0*
1)
1(
0'
b0 &
1%
1$
0#
0"
b0 !
$end
#10
1#
1'
#20
1,
0#
0'
0$
0(
0%
0)
#30
1"
1-
1/
b11 !
b11 &
1#
1'
#40
0,
0#
0'
1%
1)
#50
0.
0"
0-
b1 !
b1 &
1#
1'
#60
1,
0#
0'
0%
0)
#70
0,
1*
1"
0.
1-
0/
b10 !
b10 &
1#
1'
#80
0"
0*
0#
0'
1%
1)
#90
1.
0-
b0 !
b0 &
1#
1'
#100
1,
0#
0'
0%
0)
#110
1"
1-
1/
b11 !
b11 &
1#
1'
#120
0,
0#
0'
1%
1)
#130
0.
0"
0-
b1 !
b1 &
1#
1'
