SEM-3/Verilog-Codes/lab8/l8q2.v
module tff(t,clk,reset,q);
input t,clk,reset;
output reg q;
always @(posedge clk or posedge reset)
begin
if(reset) q<=1'b0;
else begin
  if(t==1'b0) q<=q;
  else q<=~q;
end
end
endmodule

module l8q2(x,clk,reset,a);
input x,clk,reset;
output [1:0]a;
tff stg0(((a[0]&~x)|(~a[1]&a[0])),clk,reset,a[1]);
tff stg1(((a[1]&~x)|(~a[0]&~x)|(~a[1]&a[0]&x)),clk,reset,a[0]);
endmodule

SEM-3/Verilog-Codes/lab8/l8q2_tb.v
`timescale 1ns/1ns
`include "l8q2.v"
module l8q2_tb;
reg x,clk,reset;
wire [1:0]a;
l8q2 uut(x,clk,reset,a);
initial begin
  $dumpfile("l8q2_tb.vcd");
  $dumpvars(0,l8q2_tb);
  clk=1'b0;
  forever #10 clk=~clk;
end
initial begin
  x=1'b1; reset=1'b1; #20;
  x=1'b0; reset=1'b0; #20;
  x=1'b1; #20;
  x=1'b0; #20;
  x=1'b1; #20;
  x=1'b0; #20;
  x=1'b1; #20;
  $display("Test complete");
  $finish;
end
endmodule

SEM-3/Verilog-Codes/lab8/l8q2_tb.vcd
$date
	Sun Nov 19 12:02:27 2023
$end
$version
	Icarus Verilog
$end
$timescale
	1ns
$end
$scope module l8q2_tb $end
$var wire 2 ! a [1:0] $end
$var reg 1 " clk $end
$var reg 1 # reset $end
$var reg 1 $ x $end
$scope module uut $end
$var wire 2 % a [1:0] $end
$var wire 1 & clk $end
$var wire 1 ' reset $end
$var wire 1 ( x $end
$scope module stg0 $end
$var wire 1 & clk $end
$var wire 1 ' reset $end
$var wire 1 ) t $end
$var reg 1 * q $end
$upscope $end
$scope module stg1 $end
$var wire 1 & clk $end
$var wire 1 ' reset $end
$var wire 1 + t $end
$var reg 1 , q $end
$upscope $end
$upscope $end
$upscope $end
$enddefinitions $end
#0
$dumpvars
0,
0+
0*
0)
1(
1'
0&
b0 %
1$
1#
0"
b0 !
$end
#10
1"
1&
#20
1+
0"
0&
0#
0'
0$
0(
#30
0+
1)
1,
b1 !
b1 %
1"
1&
#40
1+
0"
0&
1$
1(
#50
0+
0)
0,
1*
b10 !
b10 %
1"
1&
#60
1+
0"
0&
0$
0(
#70
1)
1,
b11 !
b11 %
1"
1&
#80
0+
0)
0"
0&
1$
1(
#90
1"
1&
#100
1+
1)
0"
0&
0$
0(
#110
0)
0*
0,
b0 !
b0 %
1"
1&
#120
0+
0"
0&
1$
1(
